openlch/__init__.py
openlch/cli.py
openlch/hal.py
openlch/hal_pb_pb2.py
openlch/hal_pb_pb2_grpc.py
openlch/py.typed
openlch-0.9.0.dist-info/LICENSE
openlch-0.9.0.dist-info/METADATA
openlch-0.9.0.dist-info/WHEEL
openlch-0.9.0.dist-info/entry_points.txt
openlch-0.9.0.dist-info/top_level.txt
openlch-0.9.0.dist-info/RECORD
