Metadata-Version: 2.1
Name: openlch
Version: 0.9.0
Summary: The OpenLCH project command line interface
Home-page: https://github.com/Zeroth-Robotics/openlch-client-py
Author: OpenLCH Contributors
Requires-Python: >=3.8
License-File: LICENSE
Requires-Dist: websockets
Requires-Dist: pydantic
Requires-Dist: grpcio
Requires-Dist: protobuf ==5.28.2
Requires-Dist: click
Provides-Extra: dev
Requires-Dist: black ; extra == 'dev'
Requires-Dist: darglint ; extra == 'dev'
Requires-Dist: mypy ; extra == 'dev'
Requires-Dist: pytest ; extra == 'dev'
Requires-Dist: ruff ; extra == 'dev'
Requires-Dist: grpcio-tools ; extra == 'dev'
